LICENSE
MANIFEST.in
setup.py
iterpipes3/__init__.py
iterpipes3/testing.py
iterpipes3.egg-info/PKG-INFO
iterpipes3.egg-info/SOURCES.txt
iterpipes3.egg-info/dependency_links.txt
iterpipes3.egg-info/top_level.txt
test/test_iterpipes.py