Metadata-Version: 1.1
Name: iterpipes3
Version: 0.4
Summary: A library for running shell pipelines using shell-like syntax
Home-page: http://github.com/kelleyk/iterpipes3
Author: Kevin Kelley
Author-email: kelleyk@kelleyk.net
License: MIT
Platform: UNKNOWN
Classifier: Programming Language :: Python :: 3
Classifier: Programming Language :: Python :: 3.0
Classifier: Programming Language :: Python :: 3.1
Classifier: Programming Language :: Python :: 3.2
Classifier: Programming Language :: Python :: 3.3
Requires: six
